setup.py
funniest/__init__.py
funniest_jl.egg-info/PKG-INFO
funniest_jl.egg-info/SOURCES.txt
funniest_jl.egg-info/dependency_links.txt
funniest_jl.egg-info/not-zip-safe
funniest_jl.egg-info/top_level.txt