Metadata-Version: 1.0
Name: funniest-jl
Version: 0.1
Summary: The funniest joke in the world
Home-page: http://github.com/HoustonJ2013/funniest
Author: Jingbo Liu
Author-email: jingbo.liu2013@gmail.com
License: tem
Platform: UNKNOWN
